trytond/modules/health_genetics/COPYING
trytond/modules/health_genetics/README.rst
trytond/modules/health_genetics/__init__.py
trytond/modules/health_genetics/data/gnuhealth_commands.xml
trytond/modules/health_genetics/data/human_genes_alt_loci.xml
trytond/modules/health_genetics/data/human_genes_grch38.xml
trytond/modules/health_genetics/health_genetics.py
trytond/modules/health_genetics/health_genetics_view.xml
trytond/modules/health_genetics/icons/dna.svg
trytond/modules/health_genetics/locale/ar.po
trytond/modules/health_genetics/locale/de.po
trytond/modules/health_genetics/locale/el.po
trytond/modules/health_genetics/locale/eo.po
trytond/modules/health_genetics/locale/es.po
trytond/modules/health_genetics/locale/fr.po
trytond/modules/health_genetics/locale/health_genetics.pot
trytond/modules/health_genetics/locale/it_IT.po
trytond/modules/health_genetics/locale/ja_JP.po
trytond/modules/health_genetics/locale/ka.po
trytond/modules/health_genetics/locale/lo.po
trytond/modules/health_genetics/locale/pt_BR.po
trytond/modules/health_genetics/locale/sv.po
trytond/modules/health_genetics/locale/tr.po
trytond/modules/health_genetics/locale/uk.po
trytond/modules/health_genetics/locale/zh_CN.po
trytond/modules/health_genetics/pyproject.toml
trytond/modules/health_genetics/security/access_rights.xml
trytond/modules/health_genetics/tests/__init__.py
trytond/modules/health_genetics/tests/test_health_genetics.py
trytond/modules/health_genetics/tryton.cfg
trytond/modules/health_genetics/view/gnuhealth_gene.xml
trytond/modules/health_genetics/view/gnuhealth_gene_tree.xml
trytond/modules/health_genetics/view/gnuhealth_gene_variant.xml
trytond/modules/health_genetics/view/gnuhealth_gene_variant_phenotype.xml
trytond/modules/health_genetics/view/gnuhealth_gene_variant_phenotype_tree.xml
trytond/modules/health_genetics/view/gnuhealth_gene_variant_tree.xml
trytond/modules/health_genetics/view/gnuhealth_genetic_risk.xml
gnuhealth_genetics-5.0.2.dist-info/METADATA
gnuhealth_genetics-5.0.2.dist-info/WHEEL
gnuhealth_genetics-5.0.2.dist-info/licenses/COPYING
gnuhealth_genetics-5.0.2.dist-info/RECORD
